chapter_marker/bgt_current_show.py
chapter_marker/bgt_get_titles.py
chapter_marker/bgt_replace_text.py
chapter_marker/res/book-clock.png
chapter_marker/res/book-clock.svg
chapter_marker/res/book.png
chapter_marker/res/book.svg
chapter_marker/res/clock-end.png
chapter_marker/res/clock-end.svg
chapter_marker/res/clock-start.png
chapter_marker/res/clock-start.svg
chapter_marker/res/content-save.png
chapter_marker/res/content-save.svg
chapter_marker/res/exit-run.png
chapter_marker/res/exit-run.svg
chapter_marker/res/exit-to-app.png
chapter_marker/res/exit-to-app.svg
chapter_marker/res/skip-backward.png
chapter_marker/res/skip-backward.svg
chapter_marker/res/skip-forward.png
chapter_marker/res/skip-forward.svg
chapter_marker/resources.py
chapter_marker/resources.qrc
chapter_marker/tray.py
fakenotify2/__init__.py
chapter_marker-1.0.3.dist-info/LICENSE
chapter_marker-1.0.3.dist-info/METADATA
chapter_marker-1.0.3.dist-info/WHEEL
chapter_marker-1.0.3.dist-info/entry_points.txt
chapter_marker-1.0.3.dist-info/RECORD
