Metadata-Version: 2.1
Name: chapter-marker
Version: 1.0.3
Summary: chapter-marking utility
Home-page: https://github.com/Binaergewitter/chapter-marker
License: MIT
Keywords: chapter marks,podcast,meta data
Author: Felix Richter
Author-email: github@krebsco.de
Maintainer: Felix Richter
Maintainer-email: github@krebsco.de
Requires-Python: >=3.8,<4.0
Classifier: Development Status :: 3 - Alpha
Classifier: License :: OSI Approved :: MIT License
Classifier: Natural Language :: English
Classifier: Operating System :: POSIX :: Linux
Classifier: Programming Language :: Python
Classifier: Programming Language :: Python :: 3
Classifier: Programming Language :: Python :: 3.8
Classifier: Programming Language :: Python :: 3.9
Classifier: Programming Language :: Python :: 3.10
Classifier: Programming Language :: Python :: 3.11
Classifier: Programming Language :: Python :: Implementation :: CPython
Requires-Dist: docopt
Requires-Dist: notify2
Requires-Dist: pynput
Requires-Dist: pyqt5
Requires-Dist: requests
Project-URL: Repository, https://github.com/Binaergewitter/chapter-marker
